smsgateway/__init__.py
smsgateway/config.py
smsgateway/sink_sms.py
smsgateway/events/__init__.py
smsgateway/events/service_failed.py
smsgateway/sources/__init__.py
smsgateway/sources/facebook.py
smsgateway/sources/facebook_utils.py
smsgateway/sources/imap.py
smsgateway/sources/matrix.py
smsgateway/sources/matrix_utils.py
smsgateway/sources/signal_messenger.py
smsgateway/sources/slack.py
smsgateway/sources/sms.py
smsgateway/sources/telegram.py
smsgateway/sources/telegram_utils.py
smsgateway/sources/utils.py
smsgateway/sources/whatsapp.py
smsgateway/sources/whatsapp_layer.py
smsgateway/sources/commands/__init__.py
smsgateway/sources/commands/general.py
smsgateway/sources/commands/send_facebook.py
smsgateway/sources/commands/send_matrix.py
smsgateway/sources/commands/send_signal.py
smsgateway/sources/commands/send_sms.py
smsgateway/sources/commands/send_telegram.py
smsgateway/sources/commands/services.py
smsgateway/sources/commands/utils.py
SMSGateway-0.7.1.5.dist-info/LICENSE
SMSGateway-0.7.1.5.dist-info/METADATA
SMSGateway-0.7.1.5.dist-info/WHEEL
SMSGateway-0.7.1.5.dist-info/top_level.txt
SMSGateway-0.7.1.5.dist-info/RECORD
