Metadata-Version: 2.1
Name: SMSGateway
Version: 0.7.1.5
Summary: Forwards messages via SMS from and to instant messengers
Home-page: https://github.com/Craeckie/SMSGateway
License: Creative Commons Attribution-Noncommercial-Share Alike license
Platform: UNKNOWN
Requires-Dist: appdirs
Requires-Dist: arrow
Requires-Dist: asyncio
Requires-Dist: bs4
Requires-Dist: cryptography
Requires-Dist: fbchat
Requires-Dist: imapclient
Requires-Dist: matrix-nio[e2e]
Requires-Dist: slackclient
Requires-Dist: telethon
